odoo/addons/mail_activity_reminder/README.rst
odoo/addons/mail_activity_reminder/__init__.py
odoo/addons/mail_activity_reminder/__manifest__.py
odoo/addons/mail_activity_reminder/data/mail_activity_reminder_cron.xml
odoo/addons/mail_activity_reminder/data/mail_activity_template.xml
odoo/addons/mail_activity_reminder/i18n/fr.po
odoo/addons/mail_activity_reminder/i18n/mail_activity_reminder.pot
odoo/addons/mail_activity_reminder/i18n/pt.po
odoo/addons/mail_activity_reminder/models/__init__.py
odoo/addons/mail_activity_reminder/models/mail_activity.py
odoo/addons/mail_activity_reminder/models/mail_activity_type.py
odoo/addons/mail_activity_reminder/readme/CONFIGURE.rst
odoo/addons/mail_activity_reminder/readme/CONTRIBUTORS.rst
odoo/addons/mail_activity_reminder/readme/DESCRIPTION.rst
odoo/addons/mail_activity_reminder/static/description/icon.png
odoo/addons/mail_activity_reminder/static/description/index.html
odoo/addons/mail_activity_reminder/tests/__init__.py
odoo/addons/mail_activity_reminder/tests/test_mail_activity_reminder.py
odoo/addons/mail_activity_reminder/views/mail_activity_type.xml
odoo13_addon_mail_activity_reminder-13.0.1.0.1.dev4.dist-info/METADATA
odoo13_addon_mail_activity_reminder-13.0.1.0.1.dev4.dist-info/WHEEL
odoo13_addon_mail_activity_reminder-13.0.1.0.1.dev4.dist-info/top_level.txt
odoo13_addon_mail_activity_reminder-13.0.1.0.1.dev4.dist-info/RECORD
